framer.py
framer43-0.0.0.0.dist-info/licenses/LICENSE
framer43-0.0.0.0.dist-info/METADATA
framer43-0.0.0.0.dist-info/WHEEL
framer43-0.0.0.0.dist-info/top_level.txt
framer43-0.0.0.0.dist-info/RECORD
