Metadata-Version: 2.4
Name: framer43
Version: 0.0.0.0
Summary: A text-based 2D graphics library. Handcrafted by Senthil Arasu J
Author-email: Senthil Arasu J <jaisenthil43@gmail.com>
Maintainer-email: Senthil Arasu J <jaisenthil43@gmail.com>
License-Expression: MIT
Project-URL: Homepage, https://example.com
Project-URL: Documentation, https://readthedocs.org
Project-URL: Repository, https://github.com/me/spam.git
Classifier: Programming Language :: Python :: 3
Classifier: Operating System :: OS Independent
Requires-Python: >=3.0
License-File: LICENSE
Dynamic: license-file
